README.md
setup.py
Code/__init__.py
Code/samplexrs.py
samplexrs.egg-info/PKG-INFO
samplexrs.egg-info/SOURCES.txt
samplexrs.egg-info/dependency_links.txt
samplexrs.egg-info/requires.txt
samplexrs.egg-info/top_level.txt